MANIFEST.in
Makefile
README
setup.py
test/__init__.py
test/__init__.pyc
test/test_compile.py
test/test_compile.pyc
test/test_recipeupdate.py
test/test_recipeupdate.pyc
tiddlywebplugins/__init__.py
tiddlywebplugins/recipeupdater.py
tiddlywebplugins.recipeupdater.egg-info/PKG-INFO
tiddlywebplugins.recipeupdater.egg-info/SOURCES.txt
tiddlywebplugins.recipeupdater.egg-info/dependency_links.txt
tiddlywebplugins.recipeupdater.egg-info/namespace_packages.txt
tiddlywebplugins.recipeupdater.egg-info/not-zip-safe
tiddlywebplugins.recipeupdater.egg-info/requires.txt
tiddlywebplugins.recipeupdater.egg-info/top_level.txt