Metadata-Version: 1.0
Name: tiddlywebplugins.recipeupdater
Version: 0.1
Summary: Update a recipe entry with one or more other entries
Home-page: http://pypi.python.org/pypi/tiddlywebplugins.recipeupdater
Author: Chris Dent
Author-email: cdent@peermore.com
License: UNKNOWN
Platform: Posix; MacOS X; Windows
